<?xml version="1.0"?>
<page index="74" ttl="6" left="92.409" top="68.598" right="564.095" bottom="785.195"><sborders/><verses><verse sura="3" aya="181" cx="344.651" cy="216.623" r="9.921"/><verse sura="3" aya="182" cx="297.777" cy="259.466" r="9.921"/><verse sura="3" aya="183" cx="510.545" cy="431.086" r="9.921"/><verse sura="3" aya="184" cx="236.165" cy="473.603" r="9.921"/><verse sura="3" aya="185" cx="268.931" cy="602.262" r="9.921"/><verse sura="3" aya="186" cx="143.686" cy="729.454" r="9.921"/></verses></page>
