<?xml version="1.0"?>
<page index="76" ttl="6" left="92.409" top="68.598" right="564.095" bottom="785.195"><sborders><sborder index="4" left="-391.18" top="-42.519" right="523.842" bottom="706.932"/></sborders><verses><verse sura="3" aya="195" cx="145.451" cy="302.125" r="9.921"/><verse sura="3" aya="196" cx="226.255" cy="345.524" r="9.921"/><verse sura="3" aya="197" cx="287.222" cy="389.595" r="9.921"/><verse sura="3" aya="198" cx="193.854" cy="475.108" r="9.921"/><verse sura="3" aya="199" cx="370.507" cy="645.994" r="9.921"/><verse sura="3" aya="200" cx="142.28" cy="687.336" r="9.921"/></verses></page>
