<?xml version="1.0"?>
<page index="138" ttl="9" left="92.409" top="68.598" right="564.095" bottom="785.195"><sborders/><verses><verse sura="6" aya="82" cx="410.274" cy="174.922" r="9.921"/><verse sura="6" aya="83" cx="143.734" cy="218.042" r="9.921"/><verse sura="6" aya="84" cx="143.466" cy="347.346" r="9.921"/><verse sura="6" aya="85" cx="513.071" cy="433.161" r="9.921"/><verse sura="6" aya="86" cx="458.259" cy="476.641" r="9.921"/><verse sura="6" aya="87" cx="301.429" cy="519.48" r="9.921"/><verse sura="6" aya="88" cx="452.451" cy="604.48" r="9.921"/><verse sura="6" aya="89" cx="429.353" cy="690.148" r="9.921"/><verse sura="6" aya="90" cx="146.778" cy="732.894" r="9.921"/></verses></page>
