<?xml version="1.0"?>
<page index="150" ttl="8" left="92.409" top="68.598" right="564.095" bottom="785.195"><sborders/><verses><verse sura="6" aya="158" cx="425.495" cy="257.73" r="9.921"/><verse sura="6" aya="159" cx="511.971" cy="343.368" r="9.921"/><verse sura="6" aya="160" cx="263.736" cy="386.954" r="9.921"/><verse sura="6" aya="161" cx="424.653" cy="473.971" r="9.921"/><verse sura="6" aya="162" cx="431.242" cy="516.237" r="9.921"/><verse sura="6" aya="163" cx="512.828" cy="558.047" r="9.921"/><verse sura="6" aya="164" cx="270.007" cy="644.95" r="9.921"/><verse sura="6" aya="165" cx="145.664" cy="729.243" r="9.921"/></verses></page>
