<?xml version="1.0"?>
<page index="160" ttl="8" left="92.409" top="68.598" right="564.095" bottom="785.195"><sborders/><verses><verse sura="7" aya="74" cx="359.518" cy="260.321" r="9.921"/><verse sura="7" aya="75" cx="430.545" cy="388.988" r="9.921"/><verse sura="7" aya="76" cx="338.399" cy="431.853" r="9.921"/><verse sura="7" aya="77" cx="410.233" cy="517.744" r="9.921"/><verse sura="7" aya="78" cx="448.408" cy="560.194" r="9.921"/><verse sura="7" aya="79" cx="511.261" cy="646.092" r="9.921"/><verse sura="7" aya="80" cx="317.151" cy="689.146" r="9.921"/><verse sura="7" aya="81" cx="143.769" cy="731.668" r="9.921"/></verses></page>
