<?xml version="1.0"?>
<page index="312" ttl="15" left="92.409" top="68.598" right="564.095" bottom="785.195"><sborders><sborder index="20" left="-391.18" top="42.521" right="523.968" bottom="283.4"/></sborders><verses><verse sura="19" aya="96" cx="414.335" cy="170.641" r="9.921"/><verse sura="19" aya="97" cx="290.585" cy="213.592" r="9.921"/><verse sura="19" aya="98" cx="143.413" cy="256.315" r="9.921"/><verse sura="20" aya="1" cx="485.453" cy="386.474" r="9.921"/><verse sura="20" aya="2" cx="237.618" cy="386.915" r="9.921"/><verse sura="20" aya="3" cx="436.508" cy="430.038" r="9.921"/><verse sura="20" aya="4" cx="144.55" cy="429.468" r="9.921"/><verse sura="20" aya="5" cx="312.477" cy="472.904" r="9.921"/><verse sura="20" aya="6" cx="264.144" cy="515.476" r="9.921"/><verse sura="20" aya="7" cx="351.599" cy="558.421" r="9.921"/><verse sura="20" aya="8" cx="456.976" cy="601.169" r="9.921"/><verse sura="20" aya="9" cx="226.072" cy="600.935" r="9.921"/><verse sura="20" aya="10" cx="366.339" cy="686.835" r="9.921"/><verse sura="20" aya="11" cx="168.026" cy="686.837" r="9.921"/><verse sura="20" aya="12" cx="146.112" cy="733.661" r="9.921"/></verses></page>
