<?xml version="1.0"?>
<page index="382" ttl="8" left="92.714" top="68.598" right="564.399" bottom="785.195"><sborders/><verses><verse sura="27" aya="56" cx="224.229" cy="172.001" r="9.921"/><verse sura="27" aya="57" cx="210.998" cy="215.645" r="9.921"/><verse sura="27" aya="58" cx="248.017" cy="258.275" r="9.921"/><verse sura="27" aya="59" cx="512.294" cy="343.278" r="9.921"/><verse sura="27" aya="60" cx="147.726" cy="429.394" r="9.922"/><verse sura="27" aya="61" cx="318.999" cy="558.613" r="9.921"/><verse sura="27" aya="62" cx="263.588" cy="644.547" r="9.921"/><verse sura="27" aya="63" cx="147.151" cy="730.179" r="9.921"/></verses></page>
