<?xml version="1.0"?>
<page index="446" ttl="24" left="92.409" top="68.598" right="471.685" bottom="716.598"><sborders/><verses><verse sura="37" aya="1" cx="411.526" cy="168.784" r="9.921"/><verse sura="37" aya="2" cx="284.656" cy="169.051" r="9.921"/><verse sura="37" aya="3" cx="168.249" cy="169.686" r="9.921"/><verse sura="37" aya="4" cx="424.869" cy="212.047" r="9.921"/><verse sura="37" aya="5" cx="450.469" cy="255.069" r="9.921"/><verse sura="37" aya="6" cx="200.595" cy="255.09" r="9.921"/><verse sura="37" aya="7" cx="378.661" cy="297.62" r="9.921"/><verse sura="37" aya="8" cx="426.957" cy="340.882" r="9.921"/><verse sura="37" aya="9" cx="231.673" cy="341.631" r="9.921"/><verse sura="37" aya="10" cx="315.933" cy="383.646" r="9.921"/><verse sura="37" aya="11" cx="277.377" cy="426.966" r="9.921"/><verse sura="37" aya="12" cx="513.123" cy="469.757" r="9.921"/><verse sura="37" aya="13" cx="350.818" cy="469.85" r="9.921"/><verse sura="37" aya="14" cx="145.026" cy="469.54" r="9.921"/><verse sura="37" aya="15" cx="313.829" cy="512.958" r="9.921"/><verse sura="37" aya="16" cx="420.049" cy="555.498" r="9.921"/><verse sura="37" aya="17" cx="282.872" cy="555.871" r="9.921"/><verse sura="37" aya="18" cx="511.676" cy="597.788" r="9.921"/><verse sura="37" aya="19" cx="230.863" cy="598.656" r="9.921"/><verse sura="37" aya="20" cx="409.185" cy="641.508" r="9.921"/><verse sura="37" aya="21" cx="148.609" cy="640.888" r="9.921"/><verse sura="37" aya="22" cx="193.529" cy="684.288" r="9.921"/><verse sura="37" aya="23" cx="313.679" cy="727.738" r="9.921"/><verse sura="37" aya="24" cx="145.076" cy="727.979" r="9.921"/></verses></page>
