<?xml version="1.0"?>
<page index="527" ttl="18" left="31.181" top="68.598" right="502.866" bottom="785.195"><sborders/><verses><verse sura="53" aya="27" cx="79.461" cy="131.407" r="9.921"/><verse sura="53" aya="28" cx="386.25" cy="217.09" r="9.921"/><verse sura="53" aya="29" cx="408.3" cy="259.838" r="9.921"/><verse sura="53" aya="30" cx="262.927" cy="303.109" r="9.921"/><verse sura="53" aya="31" cx="392.574" cy="389.189" r="9.921"/><verse sura="53" aya="32" cx="387.365" cy="518.08" r="9.921"/><verse sura="53" aya="33" cx="248.534" cy="517.344" r="9.921"/><verse sura="53" aya="34" cx="449.385" cy="560.447" r="9.921"/><verse sura="53" aya="35" cx="260.053" cy="560.509" r="9.921"/><verse sura="53" aya="36" cx="409.964" cy="604.047" r="9.921"/><verse sura="53" aya="37" cx="266.362" cy="602.969" r="9.921"/><verse sura="53" aya="38" cx="449.086" cy="646.915" r="9.921"/><verse sura="53" aya="39" cx="233.292" cy="646.669" r="9.921"/><verse sura="53" aya="40" cx="447.385" cy="689.933" r="9.921"/><verse sura="53" aya="41" cx="260.582" cy="689.83" r="9.921"/><verse sura="53" aya="42" cx="83.102" cy="689.286" r="9.921"/><verse sura="53" aya="43" cx="264.514" cy="732.722" r="9.921"/><verse sura="53" aya="44" cx="85.72" cy="731.762" r="9.921"/></verses></page>
