<?xml version="1.0"?>
<page index="553" ttl="8" left="31.181" top="68.598" right="502.866" bottom="785.195"><sborders><sborder index="62" left="71.433" top="-42.521" right="462.614" bottom="108.372"/></sborders><verses><verse sura="62" aya="1" cx="399.964" cy="259.772" r="9.921"/><verse sura="62" aya="2" cx="284.868" cy="343.915" r="9.921"/><verse sura="62" aya="3" cx="332.531" cy="387.741" r="9.921"/><verse sura="62" aya="4" cx="316.123" cy="429.916" r="9.921"/><verse sura="62" aya="5" cx="447.42" cy="560.061" r="9.921"/><verse sura="62" aya="6" cx="160.493" cy="600.634" r="9.921"/><verse sura="62" aya="7" cx="103.976" cy="642.799" r="9.921"/><verse sura="62" aya="8" cx="83.131" cy="728.094" r="9.921"/></verses></page>
