<?xml version="1.0"?>
<page><border left="92.409" top="68.598" right="564.095" bottom="785.195"/><verses><verse><style>fill:#D1D3D4;stroke:#000000;stroke-width:0.5;</style><cx>451.593</cx><cy>172.984</cy><r>9.921</r></verse><verse><style>fill:#D1D3D4;stroke:#000000;stroke-width:0.5;</style><cx>169.918</cx><cy>215.207</cy><r>9.921</r></verse><verse><style>fill:#D1D3D4;stroke:#000000;stroke-width:0.5;</style><cx>146.483</cx><cy>300.574</cy><r>9.921</r></verse><verse><style>fill:#D1D3D4;stroke:#000000;stroke-width:0.5;</style><cx>171.951</cx><cy>387.245</cy><r>9.921</r></verse><verse><style>fill:#D1D3D4;stroke:#000000;stroke-width:0.5;</style><cx>329.428</cx><cy>473.565</cy><r>9.921</r></verse><verse><style>fill:#D1D3D4;stroke:#000000;stroke-width:0.5;</style><cx>233.235</cx><cy>515.806</cy><r>9.921</r></verse><verse><style>fill:#D1D3D4;stroke:#000000;stroke-width:0.5;</style><cx>179.089</cx><cy>644.232</cy><r>9.921</r></verse><verse><style>fill:#D1D3D4;stroke:#000000;stroke-width:0.5;</style><cx>437.063</cx><cy>602.075</cy><r>9.921</r></verse><verse><style>fill:#D1D3D4;stroke:#000000;stroke-width:0.5;</style><cx>142.771</cx><cy>729.935</cy><r>9.921</r></verse></verses><totalverses>9</totalverses></page>
