<?xml version="1.0"?>
<page><border left="31.181" top="68.598" right="502.866" bottom="785.195"/><verses><verse><style>fill:#D1D3D4;stroke:#000000;stroke-width:0.5;</style><cx>229.303</cx><cy>218.795</cy><r>9.921</r></verse><verse><style>fill:#D1D3D4;stroke:#000000;stroke-width:0.5;</style><cx>274.565</cx><cy>304.024</cy><r>9.921</r></verse><verse><style>fill:#D1D3D4;stroke:#000000;stroke-width:0.5;</style><cx>350.488</cx><cy>432.829</cy><r>9.921</r></verse><verse><style>fill:#D1D3D4;stroke:#000000;stroke-width:0.5;</style><cx>176.215</cx><cy>517.971</cy><r>9.921</r></verse><verse><style>fill:#D1D3D4;stroke:#000000;stroke-width:0.5;</style><cx>219.164</cx><cy>605.386</cy><r>9.921</r></verse><verse><style>fill:#D1D3D4;stroke:#000000;stroke-width:0.5;</style><cx>161.732</cx><cy>691.191</cy><r>9.921</r></verse><verse><style>fill:#D1D3D4;stroke:#000000;stroke-width:0.5;</style><cx>81.958</cx><cy>732.777</cy><r>9.921</r></verse></verses><totalverses>7</totalverses></page>
